pytest_ekstazi/__init__.py
pytest_ekstazi/config.py
pytest_ekstazi/plugin.py
pytest_ekstazi/utils.py
pytest_ekstazi-1.0.0.dist-info/LICENSE
pytest_ekstazi-1.0.0.dist-info/METADATA
pytest_ekstazi-1.0.0.dist-info/WHEEL
pytest_ekstazi-1.0.0.dist-info/entry_points.txt
pytest_ekstazi-1.0.0.dist-info/top_level.txt
pytest_ekstazi-1.0.0.dist-info/RECORD
