Metadata-Version: 2.1
Name: pytest-ekstazi
Version: 1.0.0
Summary: Pytest plugin to select test using Ekstazi algorithm
Home-page: https://github.com/Igorxp5/pytest-ekstazi
Author: Igorxp5, vsla, Nielx20
Classifier: Programming Language :: Python :: 3
Classifier: License :: OSI Approved :: MIT License
Classifier: Operating System :: OS Independent
Classifier: Framework :: Pytest
Requires-Python: >=3.7
License-File: LICENSE
Requires-Dist: pytest
